<EnterpriseApplication>
	<Sonic>
		<JMSObjects>
			<FactoryUser>EBillGatewayEARWAS</FactoryUser>
			<FactoryPW>STVCMUk1MUNjOQ==</FactoryPW>
			<ACL>
				<Principal>EBillGatewayEARWAS</Principal>
				<ResourceType>topic</ResourceType>
				<ResourceName>com.kahg.ess.cm.search.entry</ResourceName>
				<Permission>grant</Permission>
				<Action>publish</Action>
			</ACL>
			<ACL>
				<Principal>EBillGatewayEARWAS</Principal>
				<ResourceType>topic</ResourceType>
				<ResourceName>com.kahg.ess.cm.retrieve.entry</ResourceName>
				<Permission>grant</Permission>
				<Action>publish</Action>
			</ACL>
			<ACL>
				<Principal>EBillGatewayEARWAS</Principal>
				<ResourceType>queue</ResourceType>
				<ResourceName>com.kahg.ebill.security.entry</ResourceName>
				<Permission>grant</Permission>
				<Action>send</Action>
			</ACL>
			<ACL>
				<Principal>EBillGatewayEARWAS</Principal>
				<ResourceType>queue</ResourceType>
				<ResourceName>com.kahg.ebill.bark.entry</ResourceName>
				<Permission>grant</Permission>
				<Action>send</Action>
			</ACL>
			<ACL>
				<Principal>EBillGatewayEARWAS</Principal>
				<ResourceType>queue</ResourceType>
				<ResourceName>com.kahg.ebill.activation.request.entry</ResourceName>
				<Permission>grant</Permission>
				<Action>send</Action>
			</ACL>
			<ACL>
				<Principal>EBillGatewayEARWAS</Principal>
				<ResourceType>queue</ResourceType>
				<ResourceName>com.kahg.ebill.activation.confirmation.entry</ResourceName>
				<Permission>grant</Permission>
				<Action>send</Action>
			</ACL>
			<ACL>
				<Principal>EBillGatewayEARWAS</Principal>
				<ResourceType>queue</ResourceType>
				<ResourceName>com.kahg.ebill.deactivation.request.entry</ResourceName>
				<Permission>grant</Permission>
				<Action>send</Action>
			</ACL>
			<ACL>
				<Principal>EBillGatewayEARWAS</Principal>
				<ResourceType>queue</ResourceType>
				<ResourceName>com.usg.cms.search.mdp</ResourceName>
				<Permission>grant</Permission>
				<Action>send</Action>
			</ACL>
			<ACL>
				<Principal>EBillGatewayEARWAS</Principal>
				<ResourceType>queue</ResourceType>
				<ResourceName>com.usg.cms.search.mdp</ResourceName>
				<Permission>grant</Permission>
				<Action>receive</Action>
			</ACL>
			<ACL>
				<Principal>EBillGatewayEARWAS</Principal>
				<ResourceType>queue</ResourceType>
				<ResourceName>com.usg.cms.retrieve.mdp</ResourceName>
				<Permission>grant</Permission>
				<Action>send</Action>
			</ACL>
			<ACL>
				<Principal>EBillGatewayEARWAS</Principal>
				<ResourceType>queue</ResourceType>
				<ResourceName>com.usg.cms.retrieve.mdp</ResourceName>
				<Permission>grant</Permission>
				<Action>receive</Action>
			</ACL>
		</JMSObjects>
	</Sonic>
	<ear-info>
		<ear-name>EBillGateway.ear</ear-name>
		<app-name>EBillGateway</app-name>
	</ear-info>
	<mod-info>
		<module>
			<web>
				<war-file-name>EBillGatewayWAR.war</war-file-name>
				<display-name>EBillGatewayWAR</display-name>
				<virtual-host>default_host</virtual-host>
				<server-name>xmlint-ekemper-com</server-name>
			</web>
		</module>
	</mod-info>
	<Security>
		<J2CAuthData>
			<J2C>
				<Alias>EBillGatewayEAR_SONIC_CF</Alias>
				<Username>EBillGatewayEARWAS</Username>
				<Password>I5B1I51Cc9</Password>
			</J2C>
			<J2C>
				<Alias>EBillGatewayEAR_UDB_KCWSINT</Alias>
				<Username>XAGBILLSVC</Username>
				<Password>Memuzap4</Password>
			</J2C>
		</J2CAuthData>
	</Security>
	<Node>
		<NodeName>was730aINT64V70</NodeName>
		<NodeName>was730bINT64V70</NodeName>
	</Node>
	<ApplicationServer>
		<ClusterName>EBillGateway</ClusterName>
		<Instances>
			<Server>
				<EndPoints>
					<PortItem>
						<PortName>WC_defaulthost</PortName>
						<Port>9171</Port>
					</PortItem>
				</EndPoints>
				<WebContainer>
					<SessionManagement>
						<CookieName>EBGJSESSIONID</CookieName>
						<SessionTimeout>30</SessionTimeout>
						<DistributedSessionType>NONE</DistributedSessionType>
					</SessionManagement>
				</WebContainer>
				<JavaVirtualMachine>
					<InitialHeapSize>128</InitialHeapSize>
					<MaximumHeapSize>128</MaximumHeapSize>
				</JavaVirtualMachine>
				<MonitoringPolicy>
					<maximumStartupAttempts>3</maximumStartupAttempts>
					<pingInterval>60</pingInterval>
					<pingTimeout>300</pingTimeout>
					<autoRestart>true</autoRestart>
					<serverRestartState>RUNNING</serverRestartState>
				</MonitoringPolicy>
				<JVMLogs>
					<SystemOut>
						<JVMLogsSystemOutFileFormat>BASIC</JVMLogsSystemOutFileFormat>
						<JVMLogsSystemOutRolloverType>BOTH</JVMLogsSystemOutRolloverType>
						<JVMLogsSystemOutNumberOfBackupFiles>5</JVMLogsSystemOutNumberOfBackupFiles>
						<JVMLogsSystemOutRolloverSize>50</JVMLogsSystemOutRolloverSize>
						<JVMLogsSystemOutBaseHour>24</JVMLogsSystemOutBaseHour>
						<JVMLogsSystemOutRolloverPeriod>24</JVMLogsSystemOutRolloverPeriod>
						<JVMLogsSystemOutFormatWrites>true</JVMLogsSystemOutFormatWrites>
						<JVMLogsSystemOutsuppresWrites>false</JVMLogsSystemOutsuppresWrites>
						<JVMLogsSystemOutsuppressStackTrace>false</JVMLogsSystemOutsuppressStackTrace>
					</SystemOut>
					<SystemError>
						<JVMLogsSystemErrorFileFormat>BASIC</JVMLogsSystemErrorFileFormat>
						<JVMLogsSystemErrorRolloverType>BOTH</JVMLogsSystemErrorRolloverType>
						<JVMLogsSystemErrorNumberOfBackupFiles>5</JVMLogsSystemErrorNumberOfBackupFiles>
						<JVMLogsSystemErrorRolloverSize>50</JVMLogsSystemErrorRolloverSize>
						<JVMLogsSystemErrorBaseHour>24</JVMLogsSystemErrorBaseHour>
						<JVMLogsSystemErrorRolloverPeriod>24</JVMLogsSystemErrorRolloverPeriod>
						<JVMLogsSystemErrorFormatWrites>true</JVMLogsSystemErrorFormatWrites>
						<JVMLogsSystemErrorsuppresWrites>false</JVMLogsSystemErrorsuppresWrites>
						<JVMLogsSystemErrorsuppressStackTrace>false</JVMLogsSystemErrorsuppressStackTrace>
					</SystemError>
				</JVMLogs>
			</Server>
		</Instances>
	</ApplicationServer>
	<ClusterResources>
		<JMS>
			<Provider>
				<Name>SonicMQ</Name>
				<ClassPath>${SONIC_CLASSPATH}</ClassPath>
				<ExtInitCtxFactory>com.sonicsw.jndi.mfcontext.MFContextFactory</ExtInitCtxFactory>
				<ExtProviderURL>${SONIC_DOMAINMGR_URL}</ExtProviderURL>
				<CustomProperties>
					<Property>
						<Name>com.sonicsw.jndi.mfcontext.idleTimeout</Name>
						<Value>6000</Value>
					</Property>
					<Property>
						<Name>com.sonicsw.jndi.mfcontext.domain</Name>
						<Value>KAHDomain</Value>
					</Property>
					<Property>
						<Name>java.naming.security.principal</Name>
						<Value>USGClient</Value>
					</Property>
					<Property>
						<Name>java.naming.security.credentials</Name>
						<Value>USGClient</Value>
					</Property>
				</CustomProperties>
				<ConnectionFactory>
					<Name>EBillGateway_CF</Name>
					<Type>UNIFIED</Type>
					<JNDI>jms/EBillConnectionFactory</JNDI>
					<ExtJNDI>USGConnectionFactory</ExtJNDI>
					<ComponentManagedAuthAlias>EBillGatewayEAR_SONIC_CF</ComponentManagedAuthAlias>
				</ConnectionFactory>
			</Provider>
		</JMS>
		<JDBCResources>
			<DB2Provider>
				<ProviderName>DB2_JDBC_PROVIDER</ProviderName>
				<DataSource>
					<DataSourceName>EBillGateway_CWSINT</DataSourceName>
					<DataSourceJNDIName>jdbc/cwsds</DataSourceJNDIName>
					<ComponentManagedAuthAlias>EBillGateway_UDB_KCWSINT</ComponentManagedAuthAlias>
					<DataBaseName>KCWSINT</DataBaseName>
					<DataBaseDriverType>4</DataBaseDriverType>
					<DataBaseServerName>kahobtudb90.kah.Calypso.com</DataBaseServerName>
					<PortNumber>3711</PortNumber>
					<ConnectionPoolProperties>
						<ConnectionPoolTimeout>45</ConnectionPoolTimeout>
						<ConnectionPoolMaxConnections>15</ConnectionPoolMaxConnections>
						<ConnectionPoolMinConnections>0</ConnectionPoolMinConnections>
						<ConnectionPoolReapTime>45</ConnectionPoolReapTime>
						<ConnectionPoolUnusedTimeout>45</ConnectionPoolUnusedTimeout>
						<ConnectionPoolagedTimeout>0</ConnectionPoolagedTimeout>
						<ConnectionPoolPurgePolicy>EntirePool</ConnectionPoolPurgePolicy>
					</ConnectionPoolProperties>
					<WASDataSourceProperties>
						<StatementCacheSize>10</StatementCacheSize>
						<PretestSQLString>SELECT 1 FROM SYSIBM.SYSDUMMY1</PretestSQLString>
						<PretestConnectionEnable>NO</PretestConnectionEnable>
					</WASDataSourceProperties>
				</DataSource>
			</DB2Provider>
		</JDBCResources>
		<URLResources>
			<URL>
				<URLName>EBill Gateway Environment</URLName>
				<URLJNDIName>url/EBillEnvironment.xml</URLJNDIName>
				<URLSpec>file:///${APP_INSTALL_ROOT}/${WAS_CELL_NAME}/EBillGateway.ear/EBillGatewayWAR.war/WEB-INF/classes/Environment.${deployEnv}.xml</URLSpec>
			</URL>
			<URL>
				<URLName>EBill Gateway Property</URLName>
				<URLJNDIName>url/EBillProperty.xml</URLJNDIName>
				<URLSpec>file:///${APP_INSTALL_ROOT}/${WAS_CELL_NAME}/EBillGateway.ear/EBillGatewayWAR.war/WEB-INF/classes/Property.xml</URLSpec>
			</URL>
		</URLResources>
		<NameSpaceBindings>
			<NameSpace>
				<NameSpaceType>String</NameSpaceType>
				<NameSpaceIdentifier>IDMLDAPServer0</NameSpaceIdentifier>
				<NameSpaceName>config/IDMLDAPServer0</NameSpaceName>
				<NameSpaceStringValue>ldap://ldap1-int.Calypso.com:12345/</NameSpaceStringValue>
			</NameSpace>
			<NameSpace>
				<NameSpaceType>String</NameSpaceType>
				<NameSpaceIdentifier>IDMLDAPServer1</NameSpaceIdentifier>
				<NameSpaceName>config/IDMLDAPServer1</NameSpaceName>
				<NameSpaceStringValue>ldap://ldap2-int.Calypso.com:12345/</NameSpaceStringValue>
			</NameSpace>
			<NameSpace>
				<NameSpaceType>String</NameSpaceType>
				<NameSpaceIdentifier>CMSEBILLPSWD</NameSpaceIdentifier>
				<NameSpaceName>config/CMSEBILLPSWD</NameSpaceName>
				<NameSpaceStringValue>y#ey#vE63</NameSpaceStringValue>
			</NameSpace>
			<NameSpace>
				<NameSpaceType>String</NameSpaceType>
				<NameSpaceIdentifier>CMSEBILLUID</NameSpaceIdentifier>
				<NameSpaceName>config/CMSEBILLUID</NameSpaceName>
				<NameSpaceStringValue>kahxag</NameSpaceStringValue>
			</NameSpace>
		</NameSpaceBindings>
	</ClusterResources>
</EnterpriseApplication>